{"efVersion":"0.13.6","efModuleName":["Three","Math","Vector"],"efExports":[{"TypeRef":[{"start":[1,1],"name":"src/external/Three/Math/Vector.purs","end":[121,60]},"Vector2",[]]},{"TypeRef":[{"start":[1,1],"name":"src/external/Three/Math/Vector.purs","end":[121,60]},"Vector3",[]]},{"ValueRef":[{"start":[1,1],"name":"src/external/Three/Math/Vector.purs","end":[121,60]},{"Ident":"mkVec2"}]},{"ValueRef":[{"start":[1,1],"name":"src/external/Three/Math/Vector.purs","end":[121,60]},{"Ident":"mkVec3"}]},{"TypeClassRef":[{"start":[1,1],"name":"src/external/Three/Math/Vector.purs","end":[121,60]},"HasX"]},{"ValueRef":[{"start":[1,1],"name":"src/external/Three/Math/Vector.purs","end":[121,60]},{"Ident":"vecX"}]},{"TypeClassRef":[{"start":[1,1],"name":"src/external/Three/Math/Vector.purs","end":[121,60]},"HasY"]},{"ValueRef":[{"start":[1,1],"name":"src/external/Three/Math/Vector.purs","end":[121,60]},{"Ident":"vecY"}]},{"TypeClassRef":[{"start":[1,1],"name":"src/external/Three/Math/Vector.purs","end":[121,60]},"HasZ"]},{"ValueRef":[{"start":[1,1],"name":"src/external/Three/Math/Vector.purs","end":[121,60]},{"Ident":"vecZ"}]},{"TypeClassRef":[{"start":[1,1],"name":"src/external/Three/Math/Vector.purs","end":[121,60]},"Vector"]},{"ValueRef":[{"start":[1,1],"name":"src/external/Three/Math/Vector.purs","end":[121,60]},{"Ident":"dot"}]},{"ValueOpRef":[{"start":[1,1],"name":"src/external/Three/Math/Vector.purs","end":[121,60]},"<.>"]},{"ValueOpRef":[{"start":[1,1],"name":"src/external/Three/Math/Vector.purs","end":[121,60]},"<+>"]},{"ValueOpRef":[{"start":[1,1],"name":"src/external/Three/Math/Vector.purs","end":[121,60]},"<->"]},{"ValueRef":[{"start":[1,1],"name":"src/external/Three/Math/Vector.purs","end":[121,60]},{"Ident":"length"}]},{"ValueRef":[{"start":[1,1],"name":"src/external/Three/Math/Vector.purs","end":[121,60]},{"Ident":"dist"}]},{"ValueRef":[{"start":[1,1],"name":"src/external/Three/Math/Vector.purs","end":[121,60]},{"Ident":"cross"}]},{"ValueRef":[{"start":[1,1],"name":"src/external/Three/Math/Vector.purs","end":[121,60]},{"Ident":"add"}]},{"ValueRef":[{"start":[1,1],"name":"src/external/Three/Math/Vector.purs","end":[121,60]},{"Ident":"addScaled"}]},{"ValueRef":[{"start":[1,1],"name":"src/external/Three/Math/Vector.purs","end":[121,60]},{"Ident":"sub"}]},{"ValueRef":[{"start":[1,1],"name":"src/external/Three/Math/Vector.purs","end":[121,60]},{"Ident":"normal"}]},{"ValueRef":[{"start":[1,1],"name":"src/external/Three/Math/Vector.purs","end":[121,60]},{"Ident":"multiplyScalar"}]},{"ValueRef":[{"start":[1,1],"name":"src/external/Three/Math/Vector.purs","end":[121,60]},{"Ident":"applyMatrix"}]},{"TypeInstanceRef":[{"start":[0,0],"name":"<generated>","end":[0,0]},{"Ident":"eqVec2"}]},{"TypeInstanceRef":[{"start":[0,0],"name":"<generated>","end":[0,0]},{"Ident":"eqVec3"}]},{"TypeInstanceRef":[{"start":[0,0],"name":"<generated>","end":[0,0]},{"Ident":"hasXVec2"}]},{"TypeInstanceRef":[{"start":[0,0],"name":"<generated>","end":[0,0]},{"Ident":"hasYVec2"}]},{"TypeInstanceRef":[{"start":[0,0],"name":"<generated>","end":[0,0]},{"Ident":"hasXVec3"}]},{"TypeInstanceRef":[{"start":[0,0],"name":"<generated>","end":[0,0]},{"Ident":"hasYVec3"}]},{"TypeInstanceRef":[{"start":[0,0],"name":"<generated>","end":[0,0]},{"Ident":"hasZVec3"}]},{"TypeInstanceRef":[{"start":[0,0],"name":"<generated>","end":[0,0]},{"Ident":"showVec2"}]},{"TypeInstanceRef":[{"start":[0,0],"name":"<generated>","end":[0,0]},{"Ident":"showVec3"}]},{"TypeInstanceRef":[{"start":[0,0],"name":"<generated>","end":[0,0]},{"Ident":"vecVec2"}]},{"TypeInstanceRef":[{"start":[0,0],"name":"<generated>","end":[0,0]},{"Ident":"vecVec3"}]}],"efImports":[{"eiModule":["Prim"],"eiImportType":{"Implicit":[]},"eiImportedAs":["Prim"]},{"eiModule":["Prim"],"eiImportType":{"Implicit":[]},"eiImportedAs":null},{"eiModule":["Prelude"],"eiImportType":{"Hiding":[{"ValueRef":[{"start":[8,24],"name":"src/external/Three/Math/Vector.purs","end":[8,27]},{"Ident":"add"}]},{"ValueRef":[{"start":[8,29],"name":"src/external/Three/Math/Vector.purs","end":[8,32]},{"Ident":"sub"}]}]},"eiImportedAs":null},{"eiModule":["Three","Math","Matrix"],"eiImportType":{"Explicit":[{"TypeRef":[{"start":[10,27],"name":"src/external/Three/Math/Vector.purs","end":[10,34]},"Matrix4",[]]}]},"eiImportedAs":null},{"eiModule":["Util"],"eiImportType":{"Explicit":[{"ValueRef":[{"start":[11,14],"name":"src/external/Three/Math/Vector.purs","end":[11,17]},{"Ident":"ffi"}]}]},"eiImportedAs":null}],"efFixities":[{"efAssociativity":"infixr","efPrecedence":5,"efOperator":"<.>","efAlias":[["Three","Math","Vector"],{"Left":{"Ident":"dot"}}]},{"efAssociativity":"infixr","efPrecedence":6,"efOperator":"<+>","efAlias":[["Three","Math","Vector"],{"Left":{"Ident":"add"}}]},{"efAssociativity":"infixr","efPrecedence":6,"efOperator":"<->","efAlias":[["Three","Math","Vector"],{"Left":{"Ident":"sub"}}]}],"efTypeFixities":[],"efDeclarations":[{"EDType":{"edTypeName":"Vector2","edTypeKind":{"annotation":[{"start":[13,32],"name":"src/external/Three/Math/Vector.purs","end":[13,36]},[]],"tag":"NamedKind","contents":[["Prim"],"Type"]},"edTypeDeclarationKind":"ExternData"}},{"EDType":{"edTypeName":"Vector3","edTypeKind":{"annotation":[{"start":[14,32],"name":"src/external/Three/Math/Vector.purs","end":[14,36]},[]],"tag":"NamedKind","contents":[["Prim"],"Type"]},"edTypeDeclarationKind":"ExternData"}},{"EDValue":{"edValueName":{"Ident":"mkVec2"},"edValueType":{"annotation":[{"start":[16,26],"name":"src/external/Three/Math/Vector.purs","end":[16,53]},[]],"tag":"TypeApp","contents":[{"annotation":[{"start":[16,26],"name":"src/external/Three/Math/Vector.purs","end":[16,53]},[]],"tag":"TypeApp","contents":[{"annotation":[{"start":[16,33],"name":"src/external/Three/Math/Vector.purs","end":[16,35]},[]],"tag":"TypeConstructor","contents":[["Prim"],"Function"]},{"annotation":[{"start":[16,26],"name":"src/external/Three/Math/Vector.purs","end":[16,32]},[]],"tag":"TypeConstructor","contents":[["Prim"],"Number"]}]},{"annotation":[{"start":[16,36],"name":"src/external/Three/Math/Vector.purs","end":[16,53]},[]],"tag":"TypeApp","contents":[{"annotation":[{"start":[16,36],"name":"src/external/Three/Math/Vector.purs","end":[16,53]},[]],"tag":"TypeApp","contents":[{"annotation":[{"start":[16,43],"name":"src/external/Three/Math/Vector.purs","end":[16,45]},[]],"tag":"TypeConstructor","contents":[["Prim"],"Function"]},{"annotation":[{"start":[16,36],"name":"src/external/Three/Math/Vector.purs","end":[16,42]},[]],"tag":"TypeConstructor","contents":[["Prim"],"Number"]}]},{"annotation":[{"start":[16,46],"name":"src/external/Three/Math/Vector.purs","end":[16,53]},[]],"tag":"TypeConstructor","contents":[["Three","Math","Vector"],"Vector2"]}]}]}}},{"EDValue":{"edValueName":{"Ident":"mkVec3"},"edValueType":{"annotation":[{"start":[17,26],"name":"src/external/Three/Math/Vector.purs","end":[17,63]},[]],"tag":"TypeApp","contents":[{"annotation":[{"start":[17,26],"name":"src/external/Three/Math/Vector.purs","end":[17,63]},[]],"tag":"TypeApp","contents":[{"annotation":[{"start":[17,33],"name":"src/external/Three/Math/Vector.purs","end":[17,35]},[]],"tag":"TypeConstructor","contents":[["Prim"],"Function"]},{"annotation":[{"start":[17,26],"name":"src/external/Three/Math/Vector.purs","end":[17,32]},[]],"tag":"TypeConstructor","contents":[["Prim"],"Number"]}]},{"annotation":[{"start":[17,36],"name":"src/external/Three/Math/Vector.purs","end":[17,63]},[]],"tag":"TypeApp","contents":[{"annotation":[{"start":[17,36],"name":"src/external/Three/Math/Vector.purs","end":[17,63]},[]],"tag":"TypeApp","contents":[{"annotation":[{"start":[17,43],"name":"src/external/Three/Math/Vector.purs","end":[17,45]},[]],"tag":"TypeConstructor","contents":[["Prim"],"Function"]},{"annotation":[{"start":[17,36],"name":"src/external/Three/Math/Vector.purs","end":[17,42]},[]],"tag":"TypeConstructor","contents":[["Prim"],"Number"]}]},{"annotation":[{"start":[17,46],"name":"src/external/Three/Math/Vector.purs","end":[17,63]},[]],"tag":"TypeApp","contents":[{"annotation":[{"start":[17,46],"name":"src/external/Three/Math/Vector.purs","end":[17,63]},[]],"tag":"TypeApp","contents":[{"annotation":[{"start":[17,53],"name":"src/external/Three/Math/Vector.purs","end":[17,55]},[]],"tag":"TypeConstructor","contents":[["Prim"],"Function"]},{"annotation":[{"start":[17,46],"name":"src/external/Three/Math/Vector.purs","end":[17,52]},[]],"tag":"TypeConstructor","contents":[["Prim"],"Number"]}]},{"annotation":[{"start":[17,56],"name":"src/external/Three/Math/Vector.purs","end":[17,63]},[]],"tag":"TypeConstructor","contents":[["Three","Math","Vector"],"Vector3"]}]}]}]}}},{"EDType":{"edTypeName":"HasX","edTypeKind":{"annotation":[{"start":[0,0],"name":"","end":[0,0]},[]],"tag":"FunKind","contents":[{"annotation":[{"start":[37,13],"name":"src/external/Three/Math/Vector.purs","end":[37,15]},[]],"tag":"NamedKind","contents":[["Prim"],"Type"]},{"annotation":[{"start":[0,0],"name":"","end":[0,0]},[]],"tag":"NamedKind","contents":[["Prim"],"Type"]}]},"edTypeDeclarationKind":"TypeSynonym"}},{"EDTypeSynonym":{"edTypeSynonymName":"HasX","edTypeSynonymArguments":[["a",null]],"edTypeSynonymType":{"annotation":[{"start":[0,0],"name":"","end":[0,0]},[]],"tag":"TypeApp","contents":[{"annotation":[{"start":[0,0],"name":"","end":[0,0]},[]],"tag":"TypeConstructor","contents":[["Prim"],"Record"]},{"annotation":[{"start":[0,0],"name":"","end":[0,0]},[]],"tag":"RCons","contents":["vecX",{"annotation":[{"start":[37,11],"name":"src/external/Three/Math/Vector.purs","end":[37,22]},[]],"tag":"TypeApp","contents":[{"annotation":[{"start":[37,11],"name":"src/external/Three/Math/Vector.purs","end":[37,22]},[]],"tag":"TypeApp","contents":[{"annotation":[{"start":[37,13],"name":"src/external/Three/Math/Vector.purs","end":[37,15]},[]],"tag":"TypeConstructor","contents":[["Prim"],"Function"]},{"annotation":[{"start":[37,11],"name":"src/external/Three/Math/Vector.purs","end":[37,12]},[]],"tag":"TypeVar","contents":"a"}]},{"annotation":[{"start":[37,16],"name":"src/external/Three/Math/Vector.purs","end":[37,22]},[]],"tag":"TypeConstructor","contents":[["Prim"],"Number"]}]},{"annotation":[{"start":[0,0],"name":"","end":[0,0]},[]],"tag":"REmpty"}]}]}}},{"EDClass":{"edClassName":"HasX","edClassTypeArguments":[["a",null]],"edClassMembers":[[{"Ident":"vecX"},{"annotation":[{"start":[37,11],"name":"src/external/Three/Math/Vector.purs","end":[37,22]},[]],"tag":"TypeApp","contents":[{"annotation":[{"start":[37,11],"name":"src/external/Three/Math/Vector.purs","end":[37,22]},[]],"tag":"TypeApp","contents":[{"annotation":[{"start":[37,13],"name":"src/external/Three/Math/Vector.purs","end":[37,15]},[]],"tag":"TypeConstructor","contents":[["Prim"],"Function"]},{"annotation":[{"start":[37,11],"name":"src/external/Three/Math/Vector.purs","end":[37,12]},[]],"tag":"TypeVar","contents":"a"}]},{"annotation":[{"start":[37,16],"name":"src/external/Three/Math/Vector.purs","end":[37,22]},[]],"tag":"TypeConstructor","contents":[["Prim"],"Number"]}]}]],"edClassConstraints":[],"edFunctionalDependencies":[],"edIsEmpty":false}},{"EDValue":{"edValueName":{"Ident":"vecX"},"edValueType":{"annotation":[{"start":[0,0],"name":"","end":[0,0]},[]],"tag":"ForAll","contents":["a",{"annotation":[{"start":[0,0],"name":"","end":[0,0]},[]],"tag":"ConstrainedType","contents":[{"constraintAnn":[{"start":[0,0],"name":"","end":[0,0]},[]],"constraintClass":[["Three","Math","Vector"],"HasX"],"constraintArgs":[{"annotation":[{"start":[0,0],"name":"","end":[0,0]},[]],"tag":"TypeVar","contents":"a"}],"constraintData":null},{"annotation":[{"start":[37,11],"name":"src/external/Three/Math/Vector.purs","end":[37,22]},[]],"tag":"TypeApp","contents":[{"annotation":[{"start":[37,11],"name":"src/external/Three/Math/Vector.purs","end":[37,22]},[]],"tag":"TypeApp","contents":[{"annotation":[{"start":[37,13],"name":"src/external/Three/Math/Vector.purs","end":[37,15]},[]],"tag":"TypeConstructor","contents":[["Prim"],"Function"]},{"annotation":[{"start":[37,11],"name":"src/external/Three/Math/Vector.purs","end":[37,12]},[]],"tag":"TypeVar","contents":"a"}]},{"annotation":[{"start":[37,16],"name":"src/external/Three/Math/Vector.purs","end":[37,22]},[]],"tag":"TypeConstructor","contents":[["Prim"],"Number"]}]}]},2]}}},{"EDType":{"edTypeName":"HasY","edTypeKind":{"annotation":[{"start":[0,0],"name":"","end":[0,0]},[]],"tag":"FunKind","contents":[{"annotation":[{"start":[40,13],"name":"src/external/Three/Math/Vector.purs","end":[40,15]},[]],"tag":"NamedKind","contents":[["Prim"],"Type"]},{"annotation":[{"start":[0,0],"name":"","end":[0,0]},[]],"tag":"NamedKind","contents":[["Prim"],"Type"]}]},"edTypeDeclarationKind":"TypeSynonym"}},{"EDTypeSynonym":{"edTypeSynonymName":"HasY","edTypeSynonymArguments":[["a",null]],"edTypeSynonymType":{"annotation":[{"start":[0,0],"name":"","end":[0,0]},[]],"tag":"TypeApp","contents":[{"annotation":[{"start":[0,0],"name":"","end":[0,0]},[]],"tag":"TypeConstructor","contents":[["Prim"],"Record"]},{"annotation":[{"start":[0,0],"name":"","end":[0,0]},[]],"tag":"RCons","contents":["vecY",{"annotation":[{"start":[40,11],"name":"src/external/Three/Math/Vector.purs","end":[40,22]},[]],"tag":"TypeApp","contents":[{"annotation":[{"start":[40,11],"name":"src/external/Three/Math/Vector.purs","end":[40,22]},[]],"tag":"TypeApp","contents":[{"annotation":[{"start":[40,13],"name":"src/external/Three/Math/Vector.purs","end":[40,15]},[]],"tag":"TypeConstructor","contents":[["Prim"],"Function"]},{"annotation":[{"start":[40,11],"name":"src/external/Three/Math/Vector.purs","end":[40,12]},[]],"tag":"TypeVar","contents":"a"}]},{"annotation":[{"start":[40,16],"name":"src/external/Three/Math/Vector.purs","end":[40,22]},[]],"tag":"TypeConstructor","contents":[["Prim"],"Number"]}]},{"annotation":[{"start":[0,0],"name":"","end":[0,0]},[]],"tag":"REmpty"}]}]}}},{"EDClass":{"edClassName":"HasY","edClassTypeArguments":[["a",null]],"edClassMembers":[[{"Ident":"vecY"},{"annotation":[{"start":[40,11],"name":"src/external/Three/Math/Vector.purs","end":[40,22]},[]],"tag":"TypeApp","contents":[{"annotation":[{"start":[40,11],"name":"src/external/Three/Math/Vector.purs","end":[40,22]},[]],"tag":"TypeApp","contents":[{"annotation":[{"start":[40,13],"name":"src/external/Three/Math/Vector.purs","end":[40,15]},[]],"tag":"TypeConstructor","contents":[["Prim"],"Function"]},{"annotation":[{"start":[40,11],"name":"src/external/Three/Math/Vector.purs","end":[40,12]},[]],"tag":"TypeVar","contents":"a"}]},{"annotation":[{"start":[40,16],"name":"src/external/Three/Math/Vector.purs","end":[40,22]},[]],"tag":"TypeConstructor","contents":[["Prim"],"Number"]}]}]],"edClassConstraints":[],"edFunctionalDependencies":[],"edIsEmpty":false}},{"EDValue":{"edValueName":{"Ident":"vecY"},"edValueType":{"annotation":[{"start":[0,0],"name":"","end":[0,0]},[]],"tag":"ForAll","contents":["a",{"annotation":[{"start":[0,0],"name":"","end":[0,0]},[]],"tag":"ConstrainedType","contents":[{"constraintAnn":[{"start":[0,0],"name":"","end":[0,0]},[]],"constraintClass":[["Three","Math","Vector"],"HasY"],"constraintArgs":[{"annotation":[{"start":[0,0],"name":"","end":[0,0]},[]],"tag":"TypeVar","contents":"a"}],"constraintData":null},{"annotation":[{"start":[40,11],"name":"src/external/Three/Math/Vector.purs","end":[40,22]},[]],"tag":"TypeApp","contents":[{"annotation":[{"start":[40,11],"name":"src/external/Three/Math/Vector.purs","end":[40,22]},[]],"tag":"TypeApp","contents":[{"annotation":[{"start":[40,13],"name":"src/external/Three/Math/Vector.purs","end":[40,15]},[]],"tag":"TypeConstructor","contents":[["Prim"],"Function"]},{"annotation":[{"start":[40,11],"name":"src/external/Three/Math/Vector.purs","end":[40,12]},[]],"tag":"TypeVar","contents":"a"}]},{"annotation":[{"start":[40,16],"name":"src/external/Three/Math/Vector.purs","end":[40,22]},[]],"tag":"TypeConstructor","contents":[["Prim"],"Number"]}]}]},1]}}},{"EDType":{"edTypeName":"HasZ","edTypeKind":{"annotation":[{"start":[0,0],"name":"","end":[0,0]},[]],"tag":"FunKind","contents":[{"annotation":[{"start":[43,13],"name":"src/external/Three/Math/Vector.purs","end":[43,15]},[]],"tag":"NamedKind","contents":[["Prim"],"Type"]},{"annotation":[{"start":[0,0],"name":"","end":[0,0]},[]],"tag":"NamedKind","contents":[["Prim"],"Type"]}]},"edTypeDeclarationKind":"TypeSynonym"}},{"EDTypeSynonym":{"edTypeSynonymName":"HasZ","edTypeSynonymArguments":[["a",null]],"edTypeSynonymType":{"annotation":[{"start":[0,0],"name":"","end":[0,0]},[]],"tag":"TypeApp","contents":[{"annotation":[{"start":[0,0],"name":"","end":[0,0]},[]],"tag":"TypeConstructor","contents":[["Prim"],"Record"]},{"annotation":[{"start":[0,0],"name":"","end":[0,0]},[]],"tag":"RCons","contents":["vecZ",{"annotation":[{"start":[43,11],"name":"src/external/Three/Math/Vector.purs","end":[43,22]},[]],"tag":"TypeApp","contents":[{"annotation":[{"start":[43,11],"name":"src/external/Three/Math/Vector.purs","end":[43,22]},[]],"tag":"TypeApp","contents":[{"annotation":[{"start":[43,13],"name":"src/external/Three/Math/Vector.purs","end":[43,15]},[]],"tag":"TypeConstructor","contents":[["Prim"],"Function"]},{"annotation":[{"start":[43,11],"name":"src/external/Three/Math/Vector.purs","end":[43,12]},[]],"tag":"TypeVar","contents":"a"}]},{"annotation":[{"start":[43,16],"name":"src/external/Three/Math/Vector.purs","end":[43,22]},[]],"tag":"TypeConstructor","contents":[["Prim"],"Number"]}]},{"annotation":[{"start":[0,0],"name":"","end":[0,0]},[]],"tag":"REmpty"}]}]}}},{"EDClass":{"edClassName":"HasZ","edClassTypeArguments":[["a",null]],"edClassMembers":[[{"Ident":"vecZ"},{"annotation":[{"start":[43,11],"name":"src/external/Three/Math/Vector.purs","end":[43,22]},[]],"tag":"TypeApp","contents":[{"annotation":[{"start":[43,11],"name":"src/external/Three/Math/Vector.purs","end":[43,22]},[]],"tag":"TypeApp","contents":[{"annotation":[{"start":[43,13],"name":"src/external/Three/Math/Vector.purs","end":[43,15]},[]],"tag":"TypeConstructor","contents":[["Prim"],"Function"]},{"annotation":[{"start":[43,11],"name":"src/external/Three/Math/Vector.purs","end":[43,12]},[]],"tag":"TypeVar","contents":"a"}]},{"annotation":[{"start":[43,16],"name":"src/external/Three/Math/Vector.purs","end":[43,22]},[]],"tag":"TypeConstructor","contents":[["Prim"],"Number"]}]}]],"edClassConstraints":[],"edFunctionalDependencies":[],"edIsEmpty":false}},{"EDValue":{"edValueName":{"Ident":"vecZ"},"edValueType":{"annotation":[{"start":[0,0],"name":"","end":[0,0]},[]],"tag":"ForAll","contents":["a",{"annotation":[{"start":[0,0],"name":"","end":[0,0]},[]],"tag":"ConstrainedType","contents":[{"constraintAnn":[{"start":[0,0],"name":"","end":[0,0]},[]],"constraintClass":[["Three","Math","Vector"],"HasZ"],"constraintArgs":[{"annotation":[{"start":[0,0],"name":"","end":[0,0]},[]],"tag":"TypeVar","contents":"a"}],"constraintData":null},{"annotation":[{"start":[43,11],"name":"src/external/Three/Math/Vector.purs","end":[43,22]},[]],"tag":"TypeApp","contents":[{"annotation":[{"start":[43,11],"name":"src/external/Three/Math/Vector.purs","end":[43,22]},[]],"tag":"TypeApp","contents":[{"annotation":[{"start":[43,13],"name":"src/external/Three/Math/Vector.purs","end":[43,15]},[]],"tag":"TypeConstructor","contents":[["Prim"],"Function"]},{"annotation":[{"start":[43,11],"name":"src/external/Three/Math/Vector.purs","end":[43,12]},[]],"tag":"TypeVar","contents":"a"}]},{"annotation":[{"start":[43,16],"name":"src/external/Three/Math/Vector.purs","end":[43,22]},[]],"tag":"TypeConstructor","contents":[["Prim"],"Number"]}]}]},0]}}},{"EDType":{"edTypeName":"Vector","edTypeKind":{"annotation":[{"start":[0,0],"name":"","end":[0,0]},[]],"tag":"FunKind","contents":[{"annotation":[{"start":[84,12],"name":"src/external/Three/Math/Vector.purs","end":[84,14]},[]],"tag":"NamedKind","contents":[["Prim"],"Type"]},{"annotation":[{"start":[0,0],"name":"","end":[0,0]},[]],"tag":"NamedKind","contents":[["Prim"],"Type"]}]},"edTypeDeclarationKind":"TypeSynonym"}},{"EDTypeSynonym":{"edTypeSynonymName":"Vector","edTypeSynonymArguments":[["a",null]],"edTypeSynonymType":{"annotation":[{"start":[0,0],"name":"","end":[0,0]},[]],"tag":"TypeApp","contents":[{"annotation":[{"start":[0,0],"name":"","end":[0,0]},[]],"tag":"TypeConstructor","contents":[["Prim"],"Record"]},{"annotation":[{"start":[0,0],"name":"","end":[0,0]},[]],"tag":"RCons","contents":["dot",{"annotation":[{"start":[84,10],"name":"src/external/Three/Math/Vector.purs","end":[84,26]},[]],"tag":"TypeApp","contents":[{"annotation":[{"start":[84,10],"name":"src/external/Three/Math/Vector.purs","end":[84,26]},[]],"tag":"TypeApp","contents":[{"annotation":[{"start":[84,12],"name":"src/external/Three/Math/Vector.purs","end":[84,14]},[]],"tag":"TypeConstructor","contents":[["Prim"],"Function"]},{"annotation":[{"start":[84,10],"name":"src/external/Three/Math/Vector.purs","end":[84,11]},[]],"tag":"TypeVar","contents":"a"}]},{"annotation":[{"start":[84,15],"name":"src/external/Three/Math/Vector.purs","end":[84,26]},[]],"tag":"TypeApp","contents":[{"annotation":[{"start":[84,15],"name":"src/external/Three/Math/Vector.purs","end":[84,26]},[]],"tag":"TypeApp","contents":[{"annotation":[{"start":[84,17],"name":"src/external/Three/Math/Vector.purs","end":[84,19]},[]],"tag":"TypeConstructor","contents":[["Prim"],"Function"]},{"annotation":[{"start":[84,15],"name":"src/external/Three/Math/Vector.purs","end":[84,16]},[]],"tag":"TypeVar","contents":"a"}]},{"annotation":[{"start":[84,20],"name":"src/external/Three/Math/Vector.purs","end":[84,26]},[]],"tag":"TypeConstructor","contents":[["Prim"],"Number"]}]}]},{"annotation":[{"start":[0,0],"name":"","end":[0,0]},[]],"tag":"RCons","contents":["length",{"annotation":[{"start":[85,13],"name":"src/external/Three/Math/Vector.purs","end":[85,24]},[]],"tag":"TypeApp","contents":[{"annotation":[{"start":[85,13],"name":"src/external/Three/Math/Vector.purs","end":[85,24]},[]],"tag":"TypeApp","contents":[{"annotation":[{"start":[85,15],"name":"src/external/Three/Math/Vector.purs","end":[85,17]},[]],"tag":"TypeConstructor","contents":[["Prim"],"Function"]},{"annotation":[{"start":[85,13],"name":"src/external/Three/Math/Vector.purs","end":[85,14]},[]],"tag":"TypeVar","contents":"a"}]},{"annotation":[{"start":[85,18],"name":"src/external/Three/Math/Vector.purs","end":[85,24]},[]],"tag":"TypeConstructor","contents":[["Prim"],"Number"]}]},{"annotation":[{"start":[0,0],"name":"","end":[0,0]},[]],"tag":"RCons","contents":["dist",{"annotation":[{"start":[86,11],"name":"src/external/Three/Math/Vector.purs","end":[86,27]},[]],"tag":"TypeApp","contents":[{"annotation":[{"start":[86,11],"name":"src/external/Three/Math/Vector.purs","end":[86,27]},[]],"tag":"TypeApp","contents":[{"annotation":[{"start":[86,13],"name":"src/external/Three/Math/Vector.purs","end":[86,15]},[]],"tag":"TypeConstructor","contents":[["Prim"],"Function"]},{"annotation":[{"start":[86,11],"name":"src/external/Three/Math/Vector.purs","end":[86,12]},[]],"tag":"TypeVar","contents":"a"}]},{"annotation":[{"start":[86,16],"name":"src/external/Three/Math/Vector.purs","end":[86,27]},[]],"tag":"TypeApp","contents":[{"annotation":[{"start":[86,16],"name":"src/external/Three/Math/Vector.purs","end":[86,27]},[]],"tag":"TypeApp","contents":[{"annotation":[{"start":[86,18],"name":"src/external/Three/Math/Vector.purs","end":[86,20]},[]],"tag":"TypeConstructor","contents":[["Prim"],"Function"]},{"annotation":[{"start":[86,16],"name":"src/external/Three/Math/Vector.purs","end":[86,17]},[]],"tag":"TypeVar","contents":"a"}]},{"annotation":[{"start":[86,21],"name":"src/external/Three/Math/Vector.purs","end":[86,27]},[]],"tag":"TypeConstructor","contents":[["Prim"],"Number"]}]}]},{"annotation":[{"start":[0,0],"name":"","end":[0,0]},[]],"tag":"RCons","contents":["cross",{"annotation":[{"start":[87,12],"name":"src/external/Three/Math/Vector.purs","end":[87,23]},[]],"tag":"TypeApp","contents":[{"annotation":[{"start":[87,12],"name":"src/external/Three/Math/Vector.purs","end":[87,23]},[]],"tag":"TypeApp","contents":[{"annotation":[{"start":[87,14],"name":"src/external/Three/Math/Vector.purs","end":[87,16]},[]],"tag":"TypeConstructor","contents":[["Prim"],"Function"]},{"annotation":[{"start":[87,12],"name":"src/external/Three/Math/Vector.purs","end":[87,13]},[]],"tag":"TypeVar","contents":"a"}]},{"annotation":[{"start":[87,17],"name":"src/external/Three/Math/Vector.purs","end":[87,23]},[]],"tag":"TypeApp","contents":[{"annotation":[{"start":[87,17],"name":"src/external/Three/Math/Vector.purs","end":[87,23]},[]],"tag":"TypeApp","contents":[{"annotation":[{"start":[87,19],"name":"src/external/Three/Math/Vector.purs","end":[87,21]},[]],"tag":"TypeConstructor","contents":[["Prim"],"Function"]},{"annotation":[{"start":[87,17],"name":"src/external/Three/Math/Vector.purs","end":[87,18]},[]],"tag":"TypeVar","contents":"a"}]},{"annotation":[{"start":[87,22],"name":"src/external/Three/Math/Vector.purs","end":[87,23]},[]],"tag":"TypeVar","contents":"a"}]}]},{"annotation":[{"start":[0,0],"name":"","end":[0,0]},[]],"tag":"RCons","contents":["add",{"annotation":[{"start":[88,10],"name":"src/external/Three/Math/Vector.purs","end":[88,21]},[]],"tag":"TypeApp","contents":[{"annotation":[{"start":[88,10],"name":"src/external/Three/Math/Vector.purs","end":[88,21]},[]],"tag":"TypeApp","contents":[{"annotation":[{"start":[88,12],"name":"src/external/Three/Math/Vector.purs","end":[88,14]},[]],"tag":"TypeConstructor","contents":[["Prim"],"Function"]},{"annotation":[{"start":[88,10],"name":"src/external/Three/Math/Vector.purs","end":[88,11]},[]],"tag":"TypeVar","contents":"a"}]},{"annotation":[{"start":[88,15],"name":"src/external/Three/Math/Vector.purs","end":[88,21]},[]],"tag":"TypeApp","contents":[{"annotation":[{"start":[88,15],"name":"src/external/Three/Math/Vector.purs","end":[88,21]},[]],"tag":"TypeApp","contents":[{"annotation":[{"start":[88,17],"name":"src/external/Three/Math/Vector.purs","end":[88,19]},[]],"tag":"TypeConstructor","contents":[["Prim"],"Function"]},{"annotation":[{"start":[88,15],"name":"src/external/Three/Math/Vector.purs","end":[88,16]},[]],"tag":"TypeVar","contents":"a"}]},{"annotation":[{"start":[88,20],"name":"src/external/Three/Math/Vector.purs","end":[88,21]},[]],"tag":"TypeVar","contents":"a"}]}]},{"annotation":[{"start":[0,0],"name":"","end":[0,0]},[]],"tag":"RCons","contents":["addScaled",{"annotation":[{"start":[89,16],"name":"src/external/Three/Math/Vector.purs","end":[89,37]},[]],"tag":"TypeApp","contents":[{"annotation":[{"start":[89,16],"name":"src/external/Three/Math/Vector.purs","end":[89,37]},[]],"tag":"TypeApp","contents":[{"annotation":[{"start":[89,18],"name":"src/external/Three/Math/Vector.purs","end":[89,20]},[]],"tag":"TypeConstructor","contents":[["Prim"],"Function"]},{"annotation":[{"start":[89,16],"name":"src/external/Three/Math/Vector.purs","end":[89,17]},[]],"tag":"TypeVar","contents":"a"}]},{"annotation":[{"start":[89,21],"name":"src/external/Three/Math/Vector.purs","end":[89,37]},[]],"tag":"TypeApp","contents":[{"annotation":[{"start":[89,21],"name":"src/external/Three/Math/Vector.purs","end":[89,37]},[]],"tag":"TypeApp","contents":[{"annotation":[{"start":[89,23],"name":"src/external/Three/Math/Vector.purs","end":[89,25]},[]],"tag":"TypeConstructor","contents":[["Prim"],"Function"]},{"annotation":[{"start":[89,21],"name":"src/external/Three/Math/Vector.purs","end":[89,22]},[]],"tag":"TypeVar","contents":"a"}]},{"annotation":[{"start":[89,26],"name":"src/external/Three/Math/Vector.purs","end":[89,37]},[]],"tag":"TypeApp","contents":[{"annotation":[{"start":[89,26],"name":"src/external/Three/Math/Vector.purs","end":[89,37]},[]],"tag":"TypeApp","contents":[{"annotation":[{"start":[89,33],"name":"src/external/Three/Math/Vector.purs","end":[89,35]},[]],"tag":"TypeConstructor","contents":[["Prim"],"Function"]},{"annotation":[{"start":[89,26],"name":"src/external/Three/Math/Vector.purs","end":[89,32]},[]],"tag":"TypeConstructor","contents":[["Prim"],"Number"]}]},{"annotation":[{"start":[89,36],"name":"src/external/Three/Math/Vector.purs","end":[89,37]},[]],"tag":"TypeVar","contents":"a"}]}]}]},{"annotation":[{"start":[0,0],"name":"","end":[0,0]},[]],"tag":"RCons","contents":["sub",{"annotation":[{"start":[90,10],"name":"src/external/Three/Math/Vector.purs","end":[90,21]},[]],"tag":"TypeApp","contents":[{"annotation":[{"start":[90,10],"name":"src/external/Three/Math/Vector.purs","end":[90,21]},[]],"tag":"TypeApp","contents":[{"annotation":[{"start":[90,12],"name":"src/external/Three/Math/Vector.purs","end":[90,14]},[]],"tag":"TypeConstructor","contents":[["Prim"],"Function"]},{"annotation":[{"start":[90,10],"name":"src/external/Three/Math/Vector.purs","end":[90,11]},[]],"tag":"TypeVar","contents":"a"}]},{"annotation":[{"start":[90,15],"name":"src/external/Three/Math/Vector.purs","end":[90,21]},[]],"tag":"TypeApp","contents":[{"annotation":[{"start":[90,15],"name":"src/external/Three/Math/Vector.purs","end":[90,21]},[]],"tag":"TypeApp","contents":[{"annotation":[{"start":[90,17],"name":"src/external/Three/Math/Vector.purs","end":[90,19]},[]],"tag":"TypeConstructor","contents":[["Prim"],"Function"]},{"annotation":[{"start":[90,15],"name":"src/external/Three/Math/Vector.purs","end":[90,16]},[]],"tag":"TypeVar","contents":"a"}]},{"annotation":[{"start":[90,20],"name":"src/external/Three/Math/Vector.purs","end":[90,21]},[]],"tag":"TypeVar","contents":"a"}]}]},{"annotation":[{"start":[0,0],"name":"","end":[0,0]},[]],"tag":"RCons","contents":["multiplyScalar",{"annotation":[{"start":[91,21],"name":"src/external/Three/Math/Vector.purs","end":[91,37]},[]],"tag":"TypeApp","contents":[{"annotation":[{"start":[91,21],"name":"src/external/Three/Math/Vector.purs","end":[91,37]},[]],"tag":"TypeApp","contents":[{"annotation":[{"start":[91,23],"name":"src/external/Three/Math/Vector.purs","end":[91,25]},[]],"tag":"TypeConstructor","contents":[["Prim"],"Function"]},{"annotation":[{"start":[91,21],"name":"src/external/Three/Math/Vector.purs","end":[91,22]},[]],"tag":"TypeVar","contents":"a"}]},{"annotation":[{"start":[91,26],"name":"src/external/Three/Math/Vector.purs","end":[91,37]},[]],"tag":"TypeApp","contents":[{"annotation":[{"start":[91,26],"name":"src/external/Three/Math/Vector.purs","end":[91,37]},[]],"tag":"TypeApp","contents":[{"annotation":[{"start":[91,33],"name":"src/external/Three/Math/Vector.purs","end":[91,35]},[]],"tag":"TypeConstructor","contents":[["Prim"],"Function"]},{"annotation":[{"start":[91,26],"name":"src/external/Three/Math/Vector.purs","end":[91,32]},[]],"tag":"TypeConstructor","contents":[["Prim"],"Number"]}]},{"annotation":[{"start":[91,36],"name":"src/external/Three/Math/Vector.purs","end":[91,37]},[]],"tag":"TypeVar","contents":"a"}]}]},{"annotation":[{"start":[0,0],"name":"","end":[0,0]},[]],"tag":"RCons","contents":["normal",{"annotation":[{"start":[92,13],"name":"src/external/Three/Math/Vector.purs","end":[92,19]},[]],"tag":"TypeApp","contents":[{"annotation":[{"start":[92,13],"name":"src/external/Three/Math/Vector.purs","end":[92,19]},[]],"tag":"TypeApp","contents":[{"annotation":[{"start":[92,15],"name":"src/external/Three/Math/Vector.purs","end":[92,17]},[]],"tag":"TypeConstructor","contents":[["Prim"],"Function"]},{"annotation":[{"start":[92,13],"name":"src/external/Three/Math/Vector.purs","end":[92,14]},[]],"tag":"TypeVar","contents":"a"}]},{"annotation":[{"start":[92,18],"name":"src/external/Three/Math/Vector.purs","end":[92,19]},[]],"tag":"TypeVar","contents":"a"}]},{"annotation":[{"start":[0,0],"name":"","end":[0,0]},[]],"tag":"REmpty"}]}]}]}]}]}]}]}]}]}]}}},{"EDClass":{"edClassName":"Vector","edClassTypeArguments":[["a",null]],"edClassMembers":[[{"Ident":"dot"},{"annotation":[{"start":[84,10],"name":"src/external/Three/Math/Vector.purs","end":[84,26]},[]],"tag":"TypeApp","contents":[{"annotation":[{"start":[84,10],"name":"src/external/Three/Math/Vector.purs","end":[84,26]},[]],"tag":"TypeApp","contents":[{"annotation":[{"start":[84,12],"name":"src/external/Three/Math/Vector.purs","end":[84,14]},[]],"tag":"TypeConstructor","contents":[["Prim"],"Function"]},{"annotation":[{"start":[84,10],"name":"src/external/Three/Math/Vector.purs","end":[84,11]},[]],"tag":"TypeVar","contents":"a"}]},{"annotation":[{"start":[84,15],"name":"src/external/Three/Math/Vector.purs","end":[84,26]},[]],"tag":"TypeApp","contents":[{"annotation":[{"start":[84,15],"name":"src/external/Three/Math/Vector.purs","end":[84,26]},[]],"tag":"TypeApp","contents":[{"annotation":[{"start":[84,17],"name":"src/external/Three/Math/Vector.purs","end":[84,19]},[]],"tag":"TypeConstructor","contents":[["Prim"],"Function"]},{"annotation":[{"start":[84,15],"name":"src/external/Three/Math/Vector.purs","end":[84,16]},[]],"tag":"TypeVar","contents":"a"}]},{"annotation":[{"start":[84,20],"name":"src/external/Three/Math/Vector.purs","end":[84,26]},[]],"tag":"TypeConstructor","contents":[["Prim"],"Number"]}]}]}],[{"Ident":"length"},{"annotation":[{"start":[85,13],"name":"src/external/Three/Math/Vector.purs","end":[85,24]},[]],"tag":"TypeApp","contents":[{"annotation":[{"start":[85,13],"name":"src/external/Three/Math/Vector.purs","end":[85,24]},[]],"tag":"TypeApp","contents":[{"annotation":[{"start":[85,15],"name":"src/external/Three/Math/Vector.purs","end":[85,17]},[]],"tag":"TypeConstructor","contents":[["Prim"],"Function"]},{"annotation":[{"start":[85,13],"name":"src/external/Three/Math/Vector.purs","end":[85,14]},[]],"tag":"TypeVar","contents":"a"}]},{"annotation":[{"start":[85,18],"name":"src/external/Three/Math/Vector.purs","end":[85,24]},[]],"tag":"TypeConstructor","contents":[["Prim"],"Number"]}]}],[{"Ident":"dist"},{"annotation":[{"start":[86,11],"name":"src/external/Three/Math/Vector.purs","end":[86,27]},[]],"tag":"TypeApp","contents":[{"annotation":[{"start":[86,11],"name":"src/external/Three/Math/Vector.purs","end":[86,27]},[]],"tag":"TypeApp","contents":[{"annotation":[{"start":[86,13],"name":"src/external/Three/Math/Vector.purs","end":[86,15]},[]],"tag":"TypeConstructor","contents":[["Prim"],"Function"]},{"annotation":[{"start":[86,11],"name":"src/external/Three/Math/Vector.purs","end":[86,12]},[]],"tag":"TypeVar","contents":"a"}]},{"annotation":[{"start":[86,16],"name":"src/external/Three/Math/Vector.purs","end":[86,27]},[]],"tag":"TypeApp","contents":[{"annotation":[{"start":[86,16],"name":"src/external/Three/Math/Vector.purs","end":[86,27]},[]],"tag":"TypeApp","contents":[{"annotation":[{"start":[86,18],"name":"src/external/Three/Math/Vector.purs","end":[86,20]},[]],"tag":"TypeConstructor","contents":[["Prim"],"Function"]},{"annotation":[{"start":[86,16],"name":"src/external/Three/Math/Vector.purs","end":[86,17]},[]],"tag":"TypeVar","contents":"a"}]},{"annotation":[{"start":[86,21],"name":"src/external/Three/Math/Vector.purs","end":[86,27]},[]],"tag":"TypeConstructor","contents":[["Prim"],"Number"]}]}]}],[{"Ident":"cross"},{"annotation":[{"start":[87,12],"name":"src/external/Three/Math/Vector.purs","end":[87,23]},[]],"tag":"TypeApp","contents":[{"annotation":[{"start":[87,12],"name":"src/external/Three/Math/Vector.purs","end":[87,23]},[]],"tag":"TypeApp","contents":[{"annotation":[{"start":[87,14],"name":"src/external/Three/Math/Vector.purs","end":[87,16]},[]],"tag":"TypeConstructor","contents":[["Prim"],"Function"]},{"annotation":[{"start":[87,12],"name":"src/external/Three/Math/Vector.purs","end":[87,13]},[]],"tag":"TypeVar","contents":"a"}]},{"annotation":[{"start":[87,17],"name":"src/external/Three/Math/Vector.purs","end":[87,23]},[]],"tag":"TypeApp","contents":[{"annotation":[{"start":[87,17],"name":"src/external/Three/Math/Vector.purs","end":[87,23]},[]],"tag":"TypeApp","contents":[{"annotation":[{"start":[87,19],"name":"src/external/Three/Math/Vector.purs","end":[87,21]},[]],"tag":"TypeConstructor","contents":[["Prim"],"Function"]},{"annotation":[{"start":[87,17],"name":"src/external/Three/Math/Vector.purs","end":[87,18]},[]],"tag":"TypeVar","contents":"a"}]},{"annotation":[{"start":[87,22],"name":"src/external/Three/Math/Vector.purs","end":[87,23]},[]],"tag":"TypeVar","contents":"a"}]}]}],[{"Ident":"add"},{"annotation":[{"start":[88,10],"name":"src/external/Three/Math/Vector.purs","end":[88,21]},[]],"tag":"TypeApp","contents":[{"annotation":[{"start":[88,10],"name":"src/external/Three/Math/Vector.purs","end":[88,21]},[]],"tag":"TypeApp","contents":[{"annotation":[{"start":[88,12],"name":"src/external/Three/Math/Vector.purs","end":[88,14]},[]],"tag":"TypeConstructor","contents":[["Prim"],"Function"]},{"annotation":[{"start":[88,10],"name":"src/external/Three/Math/Vector.purs","end":[88,11]},[]],"tag":"TypeVar","contents":"a"}]},{"annotation":[{"start":[88,15],"name":"src/external/Three/Math/Vector.purs","end":[88,21]},[]],"tag":"TypeApp","contents":[{"annotation":[{"start":[88,15],"name":"src/external/Three/Math/Vector.purs","end":[88,21]},[]],"tag":"TypeApp","contents":[{"annotation":[{"start":[88,17],"name":"src/external/Three/Math/Vector.purs","end":[88,19]},[]],"tag":"TypeConstructor","contents":[["Prim"],"Function"]},{"annotation":[{"start":[88,15],"name":"src/external/Three/Math/Vector.purs","end":[88,16]},[]],"tag":"TypeVar","contents":"a"}]},{"annotation":[{"start":[88,20],"name":"src/external/Three/Math/Vector.purs","end":[88,21]},[]],"tag":"TypeVar","contents":"a"}]}]}],[{"Ident":"addScaled"},{"annotation":[{"start":[89,16],"name":"src/external/Three/Math/Vector.purs","end":[89,37]},[]],"tag":"TypeApp","contents":[{"annotation":[{"start":[89,16],"name":"src/external/Three/Math/Vector.purs","end":[89,37]},[]],"tag":"TypeApp","contents":[{"annotation":[{"start":[89,18],"name":"src/external/Three/Math/Vector.purs","end":[89,20]},[]],"tag":"TypeConstructor","contents":[["Prim"],"Function"]},{"annotation":[{"start":[89,16],"name":"src/external/Three/Math/Vector.purs","end":[89,17]},[]],"tag":"TypeVar","contents":"a"}]},{"annotation":[{"start":[89,21],"name":"src/external/Three/Math/Vector.purs","end":[89,37]},[]],"tag":"TypeApp","contents":[{"annotation":[{"start":[89,21],"name":"src/external/Three/Math/Vector.purs","end":[89,37]},[]],"tag":"TypeApp","contents":[{"annotation":[{"start":[89,23],"name":"src/external/Three/Math/Vector.purs","end":[89,25]},[]],"tag":"TypeConstructor","contents":[["Prim"],"Function"]},{"annotation":[{"start":[89,21],"name":"src/external/Three/Math/Vector.purs","end":[89,22]},[]],"tag":"TypeVar","contents":"a"}]},{"annotation":[{"start":[89,26],"name":"src/external/Three/Math/Vector.purs","end":[89,37]},[]],"tag":"TypeApp","contents":[{"annotation":[{"start":[89,26],"name":"src/external/Three/Math/Vector.purs","end":[89,37]},[]],"tag":"TypeApp","contents":[{"annotation":[{"start":[89,33],"name":"src/external/Three/Math/Vector.purs","end":[89,35]},[]],"tag":"TypeConstructor","contents":[["Prim"],"Function"]},{"annotation":[{"start":[89,26],"name":"src/external/Three/Math/Vector.purs","end":[89,32]},[]],"tag":"TypeConstructor","contents":[["Prim"],"Number"]}]},{"annotation":[{"start":[89,36],"name":"src/external/Three/Math/Vector.purs","end":[89,37]},[]],"tag":"TypeVar","contents":"a"}]}]}]}],[{"Ident":"sub"},{"annotation":[{"start":[90,10],"name":"src/external/Three/Math/Vector.purs","end":[90,21]},[]],"tag":"TypeApp","contents":[{"annotation":[{"start":[90,10],"name":"src/external/Three/Math/Vector.purs","end":[90,21]},[]],"tag":"TypeApp","contents":[{"annotation":[{"start":[90,12],"name":"src/external/Three/Math/Vector.purs","end":[90,14]},[]],"tag":"TypeConstructor","contents":[["Prim"],"Function"]},{"annotation":[{"start":[90,10],"name":"src/external/Three/Math/Vector.purs","end":[90,11]},[]],"tag":"TypeVar","contents":"a"}]},{"annotation":[{"start":[90,15],"name":"src/external/Three/Math/Vector.purs","end":[90,21]},[]],"tag":"TypeApp","contents":[{"annotation":[{"start":[90,15],"name":"src/external/Three/Math/Vector.purs","end":[90,21]},[]],"tag":"TypeApp","contents":[{"annotation":[{"start":[90,17],"name":"src/external/Three/Math/Vector.purs","end":[90,19]},[]],"tag":"TypeConstructor","contents":[["Prim"],"Function"]},{"annotation":[{"start":[90,15],"name":"src/external/Three/Math/Vector.purs","end":[90,16]},[]],"tag":"TypeVar","contents":"a"}]},{"annotation":[{"start":[90,20],"name":"src/external/Three/Math/Vector.purs","end":[90,21]},[]],"tag":"TypeVar","contents":"a"}]}]}],[{"Ident":"multiplyScalar"},{"annotation":[{"start":[91,21],"name":"src/external/Three/Math/Vector.purs","end":[91,37]},[]],"tag":"TypeApp","contents":[{"annotation":[{"start":[91,21],"name":"src/external/Three/Math/Vector.purs","end":[91,37]},[]],"tag":"TypeApp","contents":[{"annotation":[{"start":[91,23],"name":"src/external/Three/Math/Vector.purs","end":[91,25]},[]],"tag":"TypeConstructor","contents":[["Prim"],"Function"]},{"annotation":[{"start":[91,21],"name":"src/external/Three/Math/Vector.purs","end":[91,22]},[]],"tag":"TypeVar","contents":"a"}]},{"annotation":[{"start":[91,26],"name":"src/external/Three/Math/Vector.purs","end":[91,37]},[]],"tag":"TypeApp","contents":[{"annotation":[{"start":[91,26],"name":"src/external/Three/Math/Vector.purs","end":[91,37]},[]],"tag":"TypeApp","contents":[{"annotation":[{"start":[91,33],"name":"src/external/Three/Math/Vector.purs","end":[91,35]},[]],"tag":"TypeConstructor","contents":[["Prim"],"Function"]},{"annotation":[{"start":[91,26],"name":"src/external/Three/Math/Vector.purs","end":[91,32]},[]],"tag":"TypeConstructor","contents":[["Prim"],"Number"]}]},{"annotation":[{"start":[91,36],"name":"src/external/Three/Math/Vector.purs","end":[91,37]},[]],"tag":"TypeVar","contents":"a"}]}]}],[{"Ident":"normal"},{"annotation":[{"start":[92,13],"name":"src/external/Three/Math/Vector.purs","end":[92,19]},[]],"tag":"TypeApp","contents":[{"annotation":[{"start":[92,13],"name":"src/external/Three/Math/Vector.purs","end":[92,19]},[]],"tag":"TypeApp","contents":[{"annotation":[{"start":[92,15],"name":"src/external/Three/Math/Vector.purs","end":[92,17]},[]],"tag":"TypeConstructor","contents":[["Prim"],"Function"]},{"annotation":[{"start":[92,13],"name":"src/external/Three/Math/Vector.purs","end":[92,14]},[]],"tag":"TypeVar","contents":"a"}]},{"annotation":[{"start":[92,18],"name":"src/external/Three/Math/Vector.purs","end":[92,19]},[]],"tag":"TypeVar","contents":"a"}]}]],"edClassConstraints":[],"edFunctionalDependencies":[],"edIsEmpty":false}},{"EDValue":{"edValueName":{"Ident":"dot"},"edValueType":{"annotation":[{"start":[0,0],"name":"","end":[0,0]},[]],"tag":"ForAll","contents":["a",{"annotation":[{"start":[0,0],"name":"","end":[0,0]},[]],"tag":"ConstrainedType","contents":[{"constraintAnn":[{"start":[0,0],"name":"","end":[0,0]},[]],"constraintClass":[["Three","Math","Vector"],"Vector"],"constraintArgs":[{"annotation":[{"start":[0,0],"name":"","end":[0,0]},[]],"tag":"TypeVar","contents":"a"}],"constraintData":null},{"annotation":[{"start":[84,10],"name":"src/external/Three/Math/Vector.purs","end":[84,26]},[]],"tag":"TypeApp","contents":[{"annotation":[{"start":[84,10],"name":"src/external/Three/Math/Vector.purs","end":[84,26]},[]],"tag":"TypeApp","contents":[{"annotation":[{"start":[84,12],"name":"src/external/Three/Math/Vector.purs","end":[84,14]},[]],"tag":"TypeConstructor","contents":[["Prim"],"Function"]},{"annotation":[{"start":[84,10],"name":"src/external/Three/Math/Vector.purs","end":[84,11]},[]],"tag":"TypeVar","contents":"a"}]},{"annotation":[{"start":[84,15],"name":"src/external/Three/Math/Vector.purs","end":[84,26]},[]],"tag":"TypeApp","contents":[{"annotation":[{"start":[84,15],"name":"src/external/Three/Math/Vector.purs","end":[84,26]},[]],"tag":"TypeApp","contents":[{"annotation":[{"start":[84,17],"name":"src/external/Three/Math/Vector.purs","end":[84,19]},[]],"tag":"TypeConstructor","contents":[["Prim"],"Function"]},{"annotation":[{"start":[84,15],"name":"src/external/Three/Math/Vector.purs","end":[84,16]},[]],"tag":"TypeVar","contents":"a"}]},{"annotation":[{"start":[84,20],"name":"src/external/Three/Math/Vector.purs","end":[84,26]},[]],"tag":"TypeConstructor","contents":[["Prim"],"Number"]}]}]}]},33]}}},{"EDValue":{"edValueName":{"Ident":"length"},"edValueType":{"annotation":[{"start":[0,0],"name":"","end":[0,0]},[]],"tag":"ForAll","contents":["a",{"annotation":[{"start":[0,0],"name":"","end":[0,0]},[]],"tag":"ConstrainedType","contents":[{"constraintAnn":[{"start":[0,0],"name":"","end":[0,0]},[]],"constraintClass":[["Three","Math","Vector"],"Vector"],"constraintArgs":[{"annotation":[{"start":[0,0],"name":"","end":[0,0]},[]],"tag":"TypeVar","contents":"a"}],"constraintData":null},{"annotation":[{"start":[85,13],"name":"src/external/Three/Math/Vector.purs","end":[85,24]},[]],"tag":"TypeApp","contents":[{"annotation":[{"start":[85,13],"name":"src/external/Three/Math/Vector.purs","end":[85,24]},[]],"tag":"TypeApp","contents":[{"annotation":[{"start":[85,15],"name":"src/external/Three/Math/Vector.purs","end":[85,17]},[]],"tag":"TypeConstructor","contents":[["Prim"],"Function"]},{"annotation":[{"start":[85,13],"name":"src/external/Three/Math/Vector.purs","end":[85,14]},[]],"tag":"TypeVar","contents":"a"}]},{"annotation":[{"start":[85,18],"name":"src/external/Three/Math/Vector.purs","end":[85,24]},[]],"tag":"TypeConstructor","contents":[["Prim"],"Number"]}]}]},24]}}},{"EDValue":{"edValueName":{"Ident":"dist"},"edValueType":{"annotation":[{"start":[0,0],"name":"","end":[0,0]},[]],"tag":"ForAll","contents":["a",{"annotation":[{"start":[0,0],"name":"","end":[0,0]},[]],"tag":"ConstrainedType","contents":[{"constraintAnn":[{"start":[0,0],"name":"","end":[0,0]},[]],"constraintClass":[["Three","Math","Vector"],"Vector"],"constraintArgs":[{"annotation":[{"start":[0,0],"name":"","end":[0,0]},[]],"tag":"TypeVar","contents":"a"}],"constraintData":null},{"annotation":[{"start":[86,11],"name":"src/external/Three/Math/Vector.purs","end":[86,27]},[]],"tag":"TypeApp","contents":[{"annotation":[{"start":[86,11],"name":"src/external/Three/Math/Vector.purs","end":[86,27]},[]],"tag":"TypeApp","contents":[{"annotation":[{"start":[86,13],"name":"src/external/Three/Math/Vector.purs","end":[86,15]},[]],"tag":"TypeConstructor","contents":[["Prim"],"Function"]},{"annotation":[{"start":[86,11],"name":"src/external/Three/Math/Vector.purs","end":[86,12]},[]],"tag":"TypeVar","contents":"a"}]},{"annotation":[{"start":[86,16],"name":"src/external/Three/Math/Vector.purs","end":[86,27]},[]],"tag":"TypeApp","contents":[{"annotation":[{"start":[86,16],"name":"src/external/Three/Math/Vector.purs","end":[86,27]},[]],"tag":"TypeApp","contents":[{"annotation":[{"start":[86,18],"name":"src/external/Three/Math/Vector.purs","end":[86,20]},[]],"tag":"TypeConstructor","contents":[["Prim"],"Function"]},{"annotation":[{"start":[86,16],"name":"src/external/Three/Math/Vector.purs","end":[86,17]},[]],"tag":"TypeVar","contents":"a"}]},{"annotation":[{"start":[86,21],"name":"src/external/Three/Math/Vector.purs","end":[86,27]},[]],"tag":"TypeConstructor","contents":[["Prim"],"Number"]}]}]}]},34]}}},{"EDValue":{"edValueName":{"Ident":"cross"},"edValueType":{"annotation":[{"start":[0,0],"name":"","end":[0,0]},[]],"tag":"ForAll","contents":["a",{"annotation":[{"start":[0,0],"name":"","end":[0,0]},[]],"tag":"ConstrainedType","contents":[{"constraintAnn":[{"start":[0,0],"name":"","end":[0,0]},[]],"constraintClass":[["Three","Math","Vector"],"Vector"],"constraintArgs":[{"annotation":[{"start":[0,0],"name":"","end":[0,0]},[]],"tag":"TypeVar","contents":"a"}],"constraintData":null},{"annotation":[{"start":[87,12],"name":"src/external/Three/Math/Vector.purs","end":[87,23]},[]],"tag":"TypeApp","contents":[{"annotation":[{"start":[87,12],"name":"src/external/Three/Math/Vector.purs","end":[87,23]},[]],"tag":"TypeApp","contents":[{"annotation":[{"start":[87,14],"name":"src/external/Three/Math/Vector.purs","end":[87,16]},[]],"tag":"TypeConstructor","contents":[["Prim"],"Function"]},{"annotation":[{"start":[87,12],"name":"src/external/Three/Math/Vector.purs","end":[87,13]},[]],"tag":"TypeVar","contents":"a"}]},{"annotation":[{"start":[87,17],"name":"src/external/Three/Math/Vector.purs","end":[87,23]},[]],"tag":"TypeApp","contents":[{"annotation":[{"start":[87,17],"name":"src/external/Three/Math/Vector.purs","end":[87,23]},[]],"tag":"TypeApp","contents":[{"annotation":[{"start":[87,19],"name":"src/external/Three/Math/Vector.purs","end":[87,21]},[]],"tag":"TypeConstructor","contents":[["Prim"],"Function"]},{"annotation":[{"start":[87,17],"name":"src/external/Three/Math/Vector.purs","end":[87,18]},[]],"tag":"TypeVar","contents":"a"}]},{"annotation":[{"start":[87,22],"name":"src/external/Three/Math/Vector.purs","end":[87,23]},[]],"tag":"TypeVar","contents":"a"}]}]}]},35]}}},{"EDValue":{"edValueName":{"Ident":"add"},"edValueType":{"annotation":[{"start":[0,0],"name":"","end":[0,0]},[]],"tag":"ForAll","contents":["a",{"annotation":[{"start":[0,0],"name":"","end":[0,0]},[]],"tag":"ConstrainedType","contents":[{"constraintAnn":[{"start":[0,0],"name":"","end":[0,0]},[]],"constraintClass":[["Three","Math","Vector"],"Vector"],"constraintArgs":[{"annotation":[{"start":[0,0],"name":"","end":[0,0]},[]],"tag":"TypeVar","contents":"a"}],"constraintData":null},{"annotation":[{"start":[88,10],"name":"src/external/Three/Math/Vector.purs","end":[88,21]},[]],"tag":"TypeApp","contents":[{"annotation":[{"start":[88,10],"name":"src/external/Three/Math/Vector.purs","end":[88,21]},[]],"tag":"TypeApp","contents":[{"annotation":[{"start":[88,12],"name":"src/external/Three/Math/Vector.purs","end":[88,14]},[]],"tag":"TypeConstructor","contents":[["Prim"],"Function"]},{"annotation":[{"start":[88,10],"name":"src/external/Three/Math/Vector.purs","end":[88,11]},[]],"tag":"TypeVar","contents":"a"}]},{"annotation":[{"start":[88,15],"name":"src/external/Three/Math/Vector.purs","end":[88,21]},[]],"tag":"TypeApp","contents":[{"annotation":[{"start":[88,15],"name":"src/external/Three/Math/Vector.purs","end":[88,21]},[]],"tag":"TypeApp","contents":[{"annotation":[{"start":[88,17],"name":"src/external/Three/Math/Vector.purs","end":[88,19]},[]],"tag":"TypeConstructor","contents":[["Prim"],"Function"]},{"annotation":[{"start":[88,15],"name":"src/external/Three/Math/Vector.purs","end":[88,16]},[]],"tag":"TypeVar","contents":"a"}]},{"annotation":[{"start":[88,20],"name":"src/external/Three/Math/Vector.purs","end":[88,21]},[]],"tag":"TypeVar","contents":"a"}]}]}]},37]}}},{"EDValue":{"edValueName":{"Ident":"addScaled"},"edValueType":{"annotation":[{"start":[0,0],"name":"","end":[0,0]},[]],"tag":"ForAll","contents":["a",{"annotation":[{"start":[0,0],"name":"","end":[0,0]},[]],"tag":"ConstrainedType","contents":[{"constraintAnn":[{"start":[0,0],"name":"","end":[0,0]},[]],"constraintClass":[["Three","Math","Vector"],"Vector"],"constraintArgs":[{"annotation":[{"start":[0,0],"name":"","end":[0,0]},[]],"tag":"TypeVar","contents":"a"}],"constraintData":null},{"annotation":[{"start":[89,16],"name":"src/external/Three/Math/Vector.purs","end":[89,37]},[]],"tag":"TypeApp","contents":[{"annotation":[{"start":[89,16],"name":"src/external/Three/Math/Vector.purs","end":[89,37]},[]],"tag":"TypeApp","contents":[{"annotation":[{"start":[89,18],"name":"src/external/Three/Math/Vector.purs","end":[89,20]},[]],"tag":"TypeConstructor","contents":[["Prim"],"Function"]},{"annotation":[{"start":[89,16],"name":"src/external/Three/Math/Vector.purs","end":[89,17]},[]],"tag":"TypeVar","contents":"a"}]},{"annotation":[{"start":[89,21],"name":"src/external/Three/Math/Vector.purs","end":[89,37]},[]],"tag":"TypeApp","contents":[{"annotation":[{"start":[89,21],"name":"src/external/Three/Math/Vector.purs","end":[89,37]},[]],"tag":"TypeApp","contents":[{"annotation":[{"start":[89,23],"name":"src/external/Three/Math/Vector.purs","end":[89,25]},[]],"tag":"TypeConstructor","contents":[["Prim"],"Function"]},{"annotation":[{"start":[89,21],"name":"src/external/Three/Math/Vector.purs","end":[89,22]},[]],"tag":"TypeVar","contents":"a"}]},{"annotation":[{"start":[89,26],"name":"src/external/Three/Math/Vector.purs","end":[89,37]},[]],"tag":"TypeApp","contents":[{"annotation":[{"start":[89,26],"name":"src/external/Three/Math/Vector.purs","end":[89,37]},[]],"tag":"TypeApp","contents":[{"annotation":[{"start":[89,33],"name":"src/external/Three/Math/Vector.purs","end":[89,35]},[]],"tag":"TypeConstructor","contents":[["Prim"],"Function"]},{"annotation":[{"start":[89,26],"name":"src/external/Three/Math/Vector.purs","end":[89,32]},[]],"tag":"TypeConstructor","contents":[["Prim"],"Number"]}]},{"annotation":[{"start":[89,36],"name":"src/external/Three/Math/Vector.purs","end":[89,37]},[]],"tag":"TypeVar","contents":"a"}]}]}]}]},36]}}},{"EDValue":{"edValueName":{"Ident":"sub"},"edValueType":{"annotation":[{"start":[0,0],"name":"","end":[0,0]},[]],"tag":"ForAll","contents":["a",{"annotation":[{"start":[0,0],"name":"","end":[0,0]},[]],"tag":"ConstrainedType","contents":[{"constraintAnn":[{"start":[0,0],"name":"","end":[0,0]},[]],"constraintClass":[["Three","Math","Vector"],"Vector"],"constraintArgs":[{"annotation":[{"start":[0,0],"name":"","end":[0,0]},[]],"tag":"TypeVar","contents":"a"}],"constraintData":null},{"annotation":[{"start":[90,10],"name":"src/external/Three/Math/Vector.purs","end":[90,21]},[]],"tag":"TypeApp","contents":[{"annotation":[{"start":[90,10],"name":"src/external/Three/Math/Vector.purs","end":[90,21]},[]],"tag":"TypeApp","contents":[{"annotation":[{"start":[90,12],"name":"src/external/Three/Math/Vector.purs","end":[90,14]},[]],"tag":"TypeConstructor","contents":[["Prim"],"Function"]},{"annotation":[{"start":[90,10],"name":"src/external/Three/Math/Vector.purs","end":[90,11]},[]],"tag":"TypeVar","contents":"a"}]},{"annotation":[{"start":[90,15],"name":"src/external/Three/Math/Vector.purs","end":[90,21]},[]],"tag":"TypeApp","contents":[{"annotation":[{"start":[90,15],"name":"src/external/Three/Math/Vector.purs","end":[90,21]},[]],"tag":"TypeApp","contents":[{"annotation":[{"start":[90,17],"name":"src/external/Three/Math/Vector.purs","end":[90,19]},[]],"tag":"TypeConstructor","contents":[["Prim"],"Function"]},{"annotation":[{"start":[90,15],"name":"src/external/Three/Math/Vector.purs","end":[90,16]},[]],"tag":"TypeVar","contents":"a"}]},{"annotation":[{"start":[90,20],"name":"src/external/Three/Math/Vector.purs","end":[90,21]},[]],"tag":"TypeVar","contents":"a"}]}]}]},21]}}},{"EDValue":{"edValueName":{"Ident":"normal"},"edValueType":{"annotation":[{"start":[0,0],"name":"","end":[0,0]},[]],"tag":"ForAll","contents":["a",{"annotation":[{"start":[0,0],"name":"","end":[0,0]},[]],"tag":"ConstrainedType","contents":[{"constraintAnn":[{"start":[0,0],"name":"","end":[0,0]},[]],"constraintClass":[["Three","Math","Vector"],"Vector"],"constraintArgs":[{"annotation":[{"start":[0,0],"name":"","end":[0,0]},[]],"tag":"TypeVar","contents":"a"}],"constraintData":null},{"annotation":[{"start":[92,13],"name":"src/external/Three/Math/Vector.purs","end":[92,19]},[]],"tag":"TypeApp","contents":[{"annotation":[{"start":[92,13],"name":"src/external/Three/Math/Vector.purs","end":[92,19]},[]],"tag":"TypeApp","contents":[{"annotation":[{"start":[92,15],"name":"src/external/Three/Math/Vector.purs","end":[92,17]},[]],"tag":"TypeConstructor","contents":[["Prim"],"Function"]},{"annotation":[{"start":[92,13],"name":"src/external/Three/Math/Vector.purs","end":[92,14]},[]],"tag":"TypeVar","contents":"a"}]},{"annotation":[{"start":[92,18],"name":"src/external/Three/Math/Vector.purs","end":[92,19]},[]],"tag":"TypeVar","contents":"a"}]}]},22]}}},{"EDValue":{"edValueName":{"Ident":"multiplyScalar"},"edValueType":{"annotation":[{"start":[0,0],"name":"","end":[0,0]},[]],"tag":"ForAll","contents":["a",{"annotation":[{"start":[0,0],"name":"","end":[0,0]},[]],"tag":"ConstrainedType","contents":[{"constraintAnn":[{"start":[0,0],"name":"","end":[0,0]},[]],"constraintClass":[["Three","Math","Vector"],"Vector"],"constraintArgs":[{"annotation":[{"start":[0,0],"name":"","end":[0,0]},[]],"tag":"TypeVar","contents":"a"}],"constraintData":null},{"annotation":[{"start":[91,21],"name":"src/external/Three/Math/Vector.purs","end":[91,37]},[]],"tag":"TypeApp","contents":[{"annotation":[{"start":[91,21],"name":"src/external/Three/Math/Vector.purs","end":[91,37]},[]],"tag":"TypeApp","contents":[{"annotation":[{"start":[91,23],"name":"src/external/Three/Math/Vector.purs","end":[91,25]},[]],"tag":"TypeConstructor","contents":[["Prim"],"Function"]},{"annotation":[{"start":[91,21],"name":"src/external/Three/Math/Vector.purs","end":[91,22]},[]],"tag":"TypeVar","contents":"a"}]},{"annotation":[{"start":[91,26],"name":"src/external/Three/Math/Vector.purs","end":[91,37]},[]],"tag":"TypeApp","contents":[{"annotation":[{"start":[91,26],"name":"src/external/Three/Math/Vector.purs","end":[91,37]},[]],"tag":"TypeApp","contents":[{"annotation":[{"start":[91,33],"name":"src/external/Three/Math/Vector.purs","end":[91,35]},[]],"tag":"TypeConstructor","contents":[["Prim"],"Function"]},{"annotation":[{"start":[91,26],"name":"src/external/Three/Math/Vector.purs","end":[91,32]},[]],"tag":"TypeConstructor","contents":[["Prim"],"Number"]}]},{"annotation":[{"start":[91,36],"name":"src/external/Three/Math/Vector.purs","end":[91,37]},[]],"tag":"TypeVar","contents":"a"}]}]}]},23]}}},{"EDValue":{"edValueName":{"Ident":"applyMatrix"},"edValueType":{"annotation":[{"start":[121,31],"name":"src/external/Three/Math/Vector.purs","end":[121,60]},[]],"tag":"TypeApp","contents":[{"annotation":[{"start":[121,31],"name":"src/external/Three/Math/Vector.purs","end":[121,60]},[]],"tag":"TypeApp","contents":[{"annotation":[{"start":[121,39],"name":"src/external/Three/Math/Vector.purs","end":[121,41]},[]],"tag":"TypeConstructor","contents":[["Prim"],"Function"]},{"annotation":[{"start":[121,31],"name":"src/external/Three/Math/Vector.purs","end":[121,38]},[]],"tag":"TypeConstructor","contents":[["Three","Math","Matrix"],"Matrix4"]}]},{"annotation":[{"start":[121,42],"name":"src/external/Three/Math/Vector.purs","end":[121,60]},[]],"tag":"TypeApp","contents":[{"annotation":[{"start":[121,42],"name":"src/external/Three/Math/Vector.purs","end":[121,60]},[]],"tag":"TypeApp","contents":[{"annotation":[{"start":[121,50],"name":"src/external/Three/Math/Vector.purs","end":[121,52]},[]],"tag":"TypeConstructor","contents":[["Prim"],"Function"]},{"annotation":[{"start":[121,42],"name":"src/external/Three/Math/Vector.purs","end":[121,49]},[]],"tag":"TypeConstructor","contents":[["Three","Math","Vector"],"Vector3"]}]},{"annotation":[{"start":[121,53],"name":"src/external/Three/Math/Vector.purs","end":[121,60]},[]],"tag":"TypeConstructor","contents":[["Three","Math","Vector"],"Vector3"]}]}]}}},{"EDInstance":{"edInstanceClassName":[["Data","Eq"],"Eq"],"edInstanceName":{"Ident":"eqVec2"},"edInstanceTypes":[{"annotation":[{"start":[21,23],"name":"src/external/Three/Math/Vector.purs","end":[21,30]},[]],"tag":"TypeConstructor","contents":[["Three","Math","Vector"],"Vector2"]}],"edInstanceConstraints":[],"edInstanceChain":[[["Three","Math","Vector"],{"Ident":"eqVec2"}]],"edInstanceChainIndex":0}},{"EDInstance":{"edInstanceClassName":[["Data","Eq"],"Eq"],"edInstanceName":{"Ident":"eqVec3"},"edInstanceTypes":[{"annotation":[{"start":[24,23],"name":"src/external/Three/Math/Vector.purs","end":[24,30]},[]],"tag":"TypeConstructor","contents":[["Three","Math","Vector"],"Vector3"]}],"edInstanceConstraints":[],"edInstanceChain":[[["Three","Math","Vector"],{"Ident":"eqVec3"}]],"edInstanceChainIndex":0}},{"EDInstance":{"edInstanceClassName":[["Three","Math","Vector"],"HasX"],"edInstanceName":{"Ident":"hasXVec2"},"edInstanceTypes":[{"annotation":[{"start":[45,27],"name":"src/external/Three/Math/Vector.purs","end":[45,34]},[]],"tag":"TypeConstructor","contents":[["Three","Math","Vector"],"Vector2"]}],"edInstanceConstraints":[],"edInstanceChain":[[["Three","Math","Vector"],{"Ident":"hasXVec2"}]],"edInstanceChainIndex":0}},{"EDInstance":{"edInstanceClassName":[["Three","Math","Vector"],"HasY"],"edInstanceName":{"Ident":"hasYVec2"},"edInstanceTypes":[{"annotation":[{"start":[48,27],"name":"src/external/Three/Math/Vector.purs","end":[48,34]},[]],"tag":"TypeConstructor","contents":[["Three","Math","Vector"],"Vector2"]}],"edInstanceConstraints":[],"edInstanceChain":[[["Three","Math","Vector"],{"Ident":"hasYVec2"}]],"edInstanceChainIndex":0}},{"EDInstance":{"edInstanceClassName":[["Three","Math","Vector"],"HasX"],"edInstanceName":{"Ident":"hasXVec3"},"edInstanceTypes":[{"annotation":[{"start":[51,27],"name":"src/external/Three/Math/Vector.purs","end":[51,34]},[]],"tag":"TypeConstructor","contents":[["Three","Math","Vector"],"Vector3"]}],"edInstanceConstraints":[],"edInstanceChain":[[["Three","Math","Vector"],{"Ident":"hasXVec3"}]],"edInstanceChainIndex":0}},{"EDInstance":{"edInstanceClassName":[["Three","Math","Vector"],"HasY"],"edInstanceName":{"Ident":"hasYVec3"},"edInstanceTypes":[{"annotation":[{"start":[54,27],"name":"src/external/Three/Math/Vector.purs","end":[54,34]},[]],"tag":"TypeConstructor","contents":[["Three","Math","Vector"],"Vector3"]}],"edInstanceConstraints":[],"edInstanceChain":[[["Three","Math","Vector"],{"Ident":"hasYVec3"}]],"edInstanceChainIndex":0}},{"EDInstance":{"edInstanceClassName":[["Three","Math","Vector"],"HasZ"],"edInstanceName":{"Ident":"hasZVec3"},"edInstanceTypes":[{"annotation":[{"start":[57,27],"name":"src/external/Three/Math/Vector.purs","end":[57,34]},[]],"tag":"TypeConstructor","contents":[["Three","Math","Vector"],"Vector3"]}],"edInstanceConstraints":[],"edInstanceChain":[[["Three","Math","Vector"],{"Ident":"hasZVec3"}]],"edInstanceChainIndex":0}},{"EDInstance":{"edInstanceClassName":[["Data","Show"],"Show"],"edInstanceName":{"Ident":"showVec2"},"edInstanceTypes":[{"annotation":[{"start":[60,27],"name":"src/external/Three/Math/Vector.purs","end":[60,34]},[]],"tag":"TypeConstructor","contents":[["Three","Math","Vector"],"Vector2"]}],"edInstanceConstraints":[],"edInstanceChain":[[["Three","Math","Vector"],{"Ident":"showVec2"}]],"edInstanceChainIndex":0}},{"EDInstance":{"edInstanceClassName":[["Data","Show"],"Show"],"edInstanceName":{"Ident":"showVec3"},"edInstanceTypes":[{"annotation":[{"start":[63,27],"name":"src/external/Three/Math/Vector.purs","end":[63,34]},[]],"tag":"TypeConstructor","contents":[["Three","Math","Vector"],"Vector3"]}],"edInstanceConstraints":[],"edInstanceChain":[[["Three","Math","Vector"],{"Ident":"showVec3"}]],"edInstanceChainIndex":0}},{"EDInstance":{"edInstanceClassName":[["Three","Math","Vector"],"Vector"],"edInstanceName":{"Ident":"vecVec2"},"edInstanceTypes":[{"annotation":[{"start":[99,28],"name":"src/external/Three/Math/Vector.purs","end":[99,35]},[]],"tag":"TypeConstructor","contents":[["Three","Math","Vector"],"Vector2"]}],"edInstanceConstraints":[],"edInstanceChain":[[["Three","Math","Vector"],{"Ident":"vecVec2"}]],"edInstanceChainIndex":0}},{"EDInstance":{"edInstanceClassName":[["Three","Math","Vector"],"Vector"],"edInstanceName":{"Ident":"vecVec3"},"edInstanceTypes":[{"annotation":[{"start":[110,28],"name":"src/external/Three/Math/Vector.purs","end":[110,35]},[]],"tag":"TypeConstructor","contents":[["Three","Math","Vector"],"Vector3"]}],"edInstanceConstraints":[],"edInstanceChain":[[["Three","Math","Vector"],{"Ident":"vecVec3"}]],"edInstanceChainIndex":0}}],"efSourceSpan":{"start":[1,1],"name":"src/external/Three/Math/Vector.purs","end":[121,60]}}