{"efVersion":"0.13.6","efModuleName":["Three","Core","WebGLRenderer"],"efExports":[{"TypeRef":[{"start":[1,1],"name":"src/external/Three/Core/WebGLRenderer.purs","end":[22,68]},"WebGLRenderer",[]]},{"ValueRef":[{"start":[1,1],"name":"src/external/Three/Core/WebGLRenderer.purs","end":[22,68]},{"Ident":"mkWebGLRenderer"}]},{"ValueRef":[{"start":[1,1],"name":"src/external/Three/Core/WebGLRenderer.purs","end":[22,68]},{"Ident":"setSize"}]},{"ValueRef":[{"start":[1,1],"name":"src/external/Three/Core/WebGLRenderer.purs","end":[22,68]},{"Ident":"domElement"}]},{"ValueRef":[{"start":[1,1],"name":"src/external/Three/Core/WebGLRenderer.purs","end":[22,68]},{"Ident":"render"}]}],"efImports":[{"eiModule":["Prim"],"eiImportType":{"Implicit":[]},"eiImportedAs":["Prim"]},{"eiModule":["Prim"],"eiImportType":{"Implicit":[]},"eiImportedAs":null},{"eiModule":["Prelude"],"eiImportType":{"Implicit":[]},"eiImportedAs":null},{"eiModule":["Effect"],"eiImportType":{"Explicit":[{"TypeRef":[{"start":[5,16],"name":"src/external/Three/Core/WebGLRenderer.purs","end":[5,22]},"Effect",[]]}]},"eiImportedAs":null},{"eiModule":["Three","Core","Camera"],"eiImportType":{"Explicit":[{"TypeRef":[{"start":[6,27],"name":"src/external/Three/Core/WebGLRenderer.purs","end":[6,33]},"Camera",[]]}]},"eiImportedAs":null},{"eiModule":["Three","Core","Scene"],"eiImportType":{"Explicit":[{"TypeRef":[{"start":[7,26],"name":"src/external/Three/Core/WebGLRenderer.purs","end":[7,31]},"Scene",[]]}]},"eiImportedAs":null},{"eiModule":["Util"],"eiImportType":{"Explicit":[{"ValueRef":[{"start":[8,14],"name":"src/external/Three/Core/WebGLRenderer.purs","end":[8,17]},{"Ident":"ffi"}]},{"ValueRef":[{"start":[8,19],"name":"src/external/Three/Core/WebGLRenderer.purs","end":[8,22]},{"Ident":"fpi"}]}]},"eiImportedAs":null},{"eiModule":["Web","DOM"],"eiImportType":{"Explicit":[{"TypeRef":[{"start":[9,17],"name":"src/external/Three/Core/WebGLRenderer.purs","end":[9,24]},"Element",[]]}]},"eiImportedAs":null}],"efFixities":[],"efTypeFixities":[],"efDeclarations":[{"EDType":{"edTypeName":"WebGLRenderer","edTypeKind":{"annotation":[{"start":[11,38],"name":"src/external/Three/Core/WebGLRenderer.purs","end":[11,42]},[]],"tag":"NamedKind","contents":[["Prim"],"Type"]},"edTypeDeclarationKind":"ExternData"}},{"EDValue":{"edValueName":{"Ident":"mkWebGLRenderer"},"edValueType":{"annotation":[{"start":[13,35],"name":"src/external/Three/Core/WebGLRenderer.purs","end":[13,55]},[]],"tag":"TypeApp","contents":[{"annotation":[{"start":[13,35],"name":"src/external/Three/Core/WebGLRenderer.purs","end":[13,41]},[]],"tag":"TypeConstructor","contents":[["Effect"],"Effect"]},{"annotation":[{"start":[13,42],"name":"src/external/Three/Core/WebGLRenderer.purs","end":[13,55]},[]],"tag":"TypeConstructor","contents":[["Three","Core","WebGLRenderer"],"WebGLRenderer"]}]}}},{"EDValue":{"edValueName":{"Ident":"setSize"},"edValueType":{"annotation":[{"start":[15,12],"name":"src/external/Three/Core/WebGLRenderer.purs","end":[15,54]},[]],"tag":"TypeApp","contents":[{"annotation":[{"start":[15,12],"name":"src/external/Three/Core/WebGLRenderer.purs","end":[15,54]},[]],"tag":"TypeApp","contents":[{"annotation":[{"start":[15,16],"name":"src/external/Three/Core/WebGLRenderer.purs","end":[15,18]},[]],"tag":"TypeConstructor","contents":[["Prim"],"Function"]},{"annotation":[{"start":[15,12],"name":"src/external/Three/Core/WebGLRenderer.purs","end":[15,15]},[]],"tag":"TypeConstructor","contents":[["Prim"],"Int"]}]},{"annotation":[{"start":[15,19],"name":"src/external/Three/Core/WebGLRenderer.purs","end":[15,54]},[]],"tag":"TypeApp","contents":[{"annotation":[{"start":[15,19],"name":"src/external/Three/Core/WebGLRenderer.purs","end":[15,54]},[]],"tag":"TypeApp","contents":[{"annotation":[{"start":[15,23],"name":"src/external/Three/Core/WebGLRenderer.purs","end":[15,25]},[]],"tag":"TypeConstructor","contents":[["Prim"],"Function"]},{"annotation":[{"start":[15,19],"name":"src/external/Three/Core/WebGLRenderer.purs","end":[15,22]},[]],"tag":"TypeConstructor","contents":[["Prim"],"Int"]}]},{"annotation":[{"start":[15,26],"name":"src/external/Three/Core/WebGLRenderer.purs","end":[15,54]},[]],"tag":"TypeApp","contents":[{"annotation":[{"start":[15,26],"name":"src/external/Three/Core/WebGLRenderer.purs","end":[15,54]},[]],"tag":"TypeApp","contents":[{"annotation":[{"start":[15,40],"name":"src/external/Three/Core/WebGLRenderer.purs","end":[15,42]},[]],"tag":"TypeConstructor","contents":[["Prim"],"Function"]},{"annotation":[{"start":[15,26],"name":"src/external/Three/Core/WebGLRenderer.purs","end":[15,39]},[]],"tag":"TypeConstructor","contents":[["Three","Core","WebGLRenderer"],"WebGLRenderer"]}]},{"annotation":[{"start":[15,43],"name":"src/external/Three/Core/WebGLRenderer.purs","end":[15,54]},[]],"tag":"TypeApp","contents":[{"annotation":[{"start":[15,43],"name":"src/external/Three/Core/WebGLRenderer.purs","end":[15,49]},[]],"tag":"TypeConstructor","contents":[["Effect"],"Effect"]},{"annotation":[{"start":[15,50],"name":"src/external/Three/Core/WebGLRenderer.purs","end":[15,54]},[]],"tag":"TypeConstructor","contents":[["Data","Unit"],"Unit"]}]}]}]}]}}},{"EDValue":{"edValueName":{"Ident":"domElement"},"edValueType":{"annotation":[{"start":[18,15],"name":"src/external/Three/Core/WebGLRenderer.purs","end":[18,39]},[]],"tag":"TypeApp","contents":[{"annotation":[{"start":[18,15],"name":"src/external/Three/Core/WebGLRenderer.purs","end":[18,39]},[]],"tag":"TypeApp","contents":[{"annotation":[{"start":[18,29],"name":"src/external/Three/Core/WebGLRenderer.purs","end":[18,31]},[]],"tag":"TypeConstructor","contents":[["Prim"],"Function"]},{"annotation":[{"start":[18,15],"name":"src/external/Three/Core/WebGLRenderer.purs","end":[18,28]},[]],"tag":"TypeConstructor","contents":[["Three","Core","WebGLRenderer"],"WebGLRenderer"]}]},{"annotation":[{"start":[18,32],"name":"src/external/Three/Core/WebGLRenderer.purs","end":[18,39]},[]],"tag":"TypeConstructor","contents":[["Web","DOM","Internal","Types"],"Element"]}]}}},{"EDValue":{"edValueName":{"Ident":"render"},"edValueType":{"annotation":[{"start":[21,11],"name":"src/external/Three/Core/WebGLRenderer.purs","end":[21,74]},[]],"tag":"ForAll","contents":["b",{"annotation":[{"start":[21,18],"name":"src/external/Three/Core/WebGLRenderer.purs","end":[21,74]},[]],"tag":"ForAll","contents":["a",{"annotation":[{"start":[21,23],"name":"src/external/Three/Core/WebGLRenderer.purs","end":[21,74]},[]],"tag":"TypeApp","contents":[{"annotation":[{"start":[21,23],"name":"src/external/Three/Core/WebGLRenderer.purs","end":[21,74]},[]],"tag":"TypeApp","contents":[{"annotation":[{"start":[21,31],"name":"src/external/Three/Core/WebGLRenderer.purs","end":[21,33]},[]],"tag":"TypeConstructor","contents":[["Prim"],"Function"]},{"annotation":[{"start":[11,16],"name":"src/external/Three/Core/Scene.purs","end":[11,36]},[]],"tag":"TypeApp","contents":[{"annotation":[{"start":[11,17],"name":"src/external/Three/Core/Object3D.purs","end":[11,27]},[]],"tag":"TypeConstructor","contents":[["Three","Core","Object3D"],"JSObject3D"]},{"annotation":[{"start":[11,26],"name":"src/external/Three/Core/Scene.purs","end":[11,35]},[]],"tag":"TypeApp","contents":[{"annotation":[{"start":[11,26],"name":"src/external/Three/Core/Scene.purs","end":[11,33]},[]],"tag":"TypeConstructor","contents":[["Three","Core","Scene"],"JSScene"]},{"annotation":[{"start":[21,29],"name":"src/external/Three/Core/WebGLRenderer.purs","end":[21,30]},[]],"tag":"TypeVar","contents":"a"}]}]}]},{"annotation":[{"start":[21,34],"name":"src/external/Three/Core/WebGLRenderer.purs","end":[21,74]},[]],"tag":"TypeApp","contents":[{"annotation":[{"start":[21,34],"name":"src/external/Three/Core/WebGLRenderer.purs","end":[21,74]},[]],"tag":"TypeApp","contents":[{"annotation":[{"start":[21,43],"name":"src/external/Three/Core/WebGLRenderer.purs","end":[21,45]},[]],"tag":"TypeConstructor","contents":[["Prim"],"Function"]},{"annotation":[{"start":[11,17],"name":"src/external/Three/Core/Camera.purs","end":[11,38]},[]],"tag":"TypeApp","contents":[{"annotation":[{"start":[11,17],"name":"src/external/Three/Core/Object3D.purs","end":[11,27]},[]],"tag":"TypeConstructor","contents":[["Three","Core","Object3D"],"JSObject3D"]},{"annotation":[{"start":[11,27],"name":"src/external/Three/Core/Camera.purs","end":[11,37]},[]],"tag":"TypeApp","contents":[{"annotation":[{"start":[11,27],"name":"src/external/Three/Core/Camera.purs","end":[11,35]},[]],"tag":"TypeConstructor","contents":[["Three","Core","Camera"],"JSCamera"]},{"annotation":[{"start":[21,41],"name":"src/external/Three/Core/WebGLRenderer.purs","end":[21,42]},[]],"tag":"TypeVar","contents":"b"}]}]}]},{"annotation":[{"start":[21,46],"name":"src/external/Three/Core/WebGLRenderer.purs","end":[21,74]},[]],"tag":"TypeApp","contents":[{"annotation":[{"start":[21,46],"name":"src/external/Three/Core/WebGLRenderer.purs","end":[21,74]},[]],"tag":"TypeApp","contents":[{"annotation":[{"start":[21,60],"name":"src/external/Three/Core/WebGLRenderer.purs","end":[21,62]},[]],"tag":"TypeConstructor","contents":[["Prim"],"Function"]},{"annotation":[{"start":[21,46],"name":"src/external/Three/Core/WebGLRenderer.purs","end":[21,59]},[]],"tag":"TypeConstructor","contents":[["Three","Core","WebGLRenderer"],"WebGLRenderer"]}]},{"annotation":[{"start":[21,63],"name":"src/external/Three/Core/WebGLRenderer.purs","end":[21,74]},[]],"tag":"TypeApp","contents":[{"annotation":[{"start":[21,63],"name":"src/external/Three/Core/WebGLRenderer.purs","end":[21,69]},[]],"tag":"TypeConstructor","contents":[["Effect"],"Effect"]},{"annotation":[{"start":[21,70],"name":"src/external/Three/Core/WebGLRenderer.purs","end":[21,74]},[]],"tag":"TypeConstructor","contents":[["Data","Unit"],"Unit"]}]}]}]}]},0]},1]}}}],"efSourceSpan":{"start":[1,1],"name":"src/external/Three/Core/WebGLRenderer.purs","end":[22,68]}}