{"reExports":[],"name":"Web.DOM.ParentNode","comments":null,"declarations":[{"children":[],"comments":null,"title":"ParentNode","info":{"kind":{"annotation":[],"tag":"NamedKind","contents":[["Prim"],"Type"]},"declType":"externData"},"sourceSpan":{"start":[22,1],"name":".spago/web-dom/v4.0.0/src/Web/DOM/ParentNode.purs","end":[22,39]}},{"children":[],"comments":"The child elements for the node.\n","title":"children","info":{"declType":"value","type":{"annotation":[],"tag":"TypeApp","contents":[{"annotation":[],"tag":"TypeApp","contents":[{"annotation":[],"tag":"TypeConstructor","contents":[["Prim"],"Function"]},{"annotation":[],"tag":"TypeConstructor","contents":[["Web","DOM","ParentNode"],"ParentNode"]}]},{"annotation":[],"tag":"TypeApp","contents":[{"annotation":[],"tag":"TypeConstructor","contents":[["Effect"],"Effect"]},{"annotation":[],"tag":"TypeConstructor","contents":[["Web","DOM","Internal","Types"],"HTMLCollection"]}]}]}},"sourceSpan":{"start":[25,1],"name":".spago/web-dom/v4.0.0/src/Web/DOM/ParentNode.purs","end":[25,63]}},{"children":[],"comments":"The first child that is an element, or Nothing if no such element exists.\n","title":"firstElementChild","info":{"declType":"value","type":{"annotation":[],"tag":"TypeApp","contents":[{"annotation":[],"tag":"TypeApp","contents":[{"annotation":[],"tag":"TypeConstructor","contents":[["Prim"],"Function"]},{"annotation":[],"tag":"TypeConstructor","contents":[["Web","DOM","ParentNode"],"ParentNode"]}]},{"annotation":[],"tag":"TypeApp","contents":[{"annotation":[],"tag":"TypeConstructor","contents":[["Effect"],"Effect"]},{"annotation":[],"tag":"ParensInType","contents":{"annotation":[],"tag":"TypeApp","contents":[{"annotation":[],"tag":"TypeConstructor","contents":[["Data","Maybe"],"Maybe"]},{"annotation":[],"tag":"TypeConstructor","contents":[["Web","DOM","Internal","Types"],"Element"]}]}}]}]}},"sourceSpan":{"start":[28,1],"name":".spago/web-dom/v4.0.0/src/Web/DOM/ParentNode.purs","end":[28,58]}},{"children":[],"comments":"The last child that is an element, or Nothing if no such element exists.\n","title":"lastElementChild","info":{"declType":"value","type":{"annotation":[],"tag":"TypeApp","contents":[{"annotation":[],"tag":"TypeApp","contents":[{"annotation":[],"tag":"TypeConstructor","contents":[["Prim"],"Function"]},{"annotation":[],"tag":"TypeConstructor","contents":[["Web","DOM","ParentNode"],"ParentNode"]}]},{"annotation":[],"tag":"TypeApp","contents":[{"annotation":[],"tag":"TypeConstructor","contents":[["Effect"],"Effect"]},{"annotation":[],"tag":"ParensInType","contents":{"annotation":[],"tag":"TypeApp","contents":[{"annotation":[],"tag":"TypeConstructor","contents":[["Data","Maybe"],"Maybe"]},{"annotation":[],"tag":"TypeConstructor","contents":[["Web","DOM","Internal","Types"],"Element"]}]}}]}]}},"sourceSpan":{"start":[34,1],"name":".spago/web-dom/v4.0.0/src/Web/DOM/ParentNode.purs","end":[34,57]}},{"children":[],"comments":"The number of child elements.\n","title":"childElementCount","info":{"declType":"value","type":{"annotation":[],"tag":"TypeApp","contents":[{"annotation":[],"tag":"TypeApp","contents":[{"annotation":[],"tag":"TypeConstructor","contents":[["Prim"],"Function"]},{"annotation":[],"tag":"TypeConstructor","contents":[["Web","DOM","ParentNode"],"ParentNode"]}]},{"annotation":[],"tag":"TypeApp","contents":[{"annotation":[],"tag":"TypeConstructor","contents":[["Effect"],"Effect"]},{"annotation":[],"tag":"TypeConstructor","contents":[["Prim"],"Int"]}]}]}},"sourceSpan":{"start":[40,1],"name":".spago/web-dom/v4.0.0/src/Web/DOM/ParentNode.purs","end":[40,61]}},{"children":[{"comments":null,"title":"QuerySelector","info":{"arguments":[{"annotation":[],"tag":"TypeConstructor","contents":[["Prim"],"String"]}],"declType":"dataConstructor"},"sourceSpan":null},{"comments":null,"title":"eqQuerySelector","info":{"declType":"instance","dependencies":[],"type":{"annotation":[],"tag":"TypeApp","contents":[{"annotation":[],"tag":"TypeConstructor","contents":[["Data","Eq"],"Eq"]},{"annotation":[],"tag":"TypeConstructor","contents":[["Web","DOM","ParentNode"],"QuerySelector"]}]}},"sourceSpan":{"start":[44,1],"name":".spago/web-dom/v4.0.0/src/Web/DOM/ParentNode.purs","end":[44,60]}},{"comments":null,"title":"ordQuerySelector","info":{"declType":"instance","dependencies":[],"type":{"annotation":[],"tag":"TypeApp","contents":[{"annotation":[],"tag":"TypeConstructor","contents":[["Data","Ord"],"Ord"]},{"annotation":[],"tag":"TypeConstructor","contents":[["Web","DOM","ParentNode"],"QuerySelector"]}]}},"sourceSpan":{"start":[45,1],"name":".spago/web-dom/v4.0.0/src/Web/DOM/ParentNode.purs","end":[45,62]}},{"comments":null,"title":"newtypeQuerySelector","info":{"declType":"instance","dependencies":[],"type":{"annotation":[],"tag":"TypeApp","contents":[{"annotation":[],"tag":"TypeApp","contents":[{"annotation":[],"tag":"TypeConstructor","contents":[["Data","Newtype"],"Newtype"]},{"annotation":[],"tag":"TypeConstructor","contents":[["Web","DOM","ParentNode"],"QuerySelector"]}]},{"annotation":[],"tag":"TypeWildcard","contents":null}]}},"sourceSpan":{"start":[46,1],"name":".spago/web-dom/v4.0.0/src/Web/DOM/ParentNode.purs","end":[46,64]}}],"comments":null,"title":"QuerySelector","info":{"declType":"data","dataDeclType":"newtype","typeArguments":[]},"sourceSpan":{"start":[42,1],"name":".spago/web-dom/v4.0.0/src/Web/DOM/ParentNode.purs","end":[42,45]}},{"children":[],"comments":"Finds the first child that is an element that matches the selector(s), or\nNothing if no such element exists.\n","title":"querySelector","info":{"declType":"value","type":{"annotation":[],"tag":"TypeApp","contents":[{"annotation":[],"tag":"TypeApp","contents":[{"annotation":[],"tag":"TypeConstructor","contents":[["Prim"],"Function"]},{"annotation":[],"tag":"TypeConstructor","contents":[["Web","DOM","ParentNode"],"QuerySelector"]}]},{"annotation":[],"tag":"TypeApp","contents":[{"annotation":[],"tag":"TypeApp","contents":[{"annotation":[],"tag":"TypeConstructor","contents":[["Prim"],"Function"]},{"annotation":[],"tag":"TypeConstructor","contents":[["Web","DOM","ParentNode"],"ParentNode"]}]},{"annotation":[],"tag":"TypeApp","contents":[{"annotation":[],"tag":"TypeConstructor","contents":[["Effect"],"Effect"]},{"annotation":[],"tag":"ParensInType","contents":{"annotation":[],"tag":"TypeApp","contents":[{"annotation":[],"tag":"TypeConstructor","contents":[["Data","Maybe"],"Maybe"]},{"annotation":[],"tag":"TypeConstructor","contents":[["Web","DOM","Internal","Types"],"Element"]}]}}]}]}]}},"sourceSpan":{"start":[50,1],"name":".spago/web-dom/v4.0.0/src/Web/DOM/ParentNode.purs","end":[50,71]}},{"children":[],"comments":"Finds all the child elements that matches the selector(s).\n","title":"querySelectorAll","info":{"declType":"value","type":{"annotation":[],"tag":"TypeApp","contents":[{"annotation":[],"tag":"TypeApp","contents":[{"annotation":[],"tag":"TypeConstructor","contents":[["Prim"],"Function"]},{"annotation":[],"tag":"TypeConstructor","contents":[["Web","DOM","ParentNode"],"QuerySelector"]}]},{"annotation":[],"tag":"TypeApp","contents":[{"annotation":[],"tag":"TypeApp","contents":[{"annotation":[],"tag":"TypeConstructor","contents":[["Prim"],"Function"]},{"annotation":[],"tag":"TypeConstructor","contents":[["Web","DOM","ParentNode"],"ParentNode"]}]},{"annotation":[],"tag":"TypeApp","contents":[{"annotation":[],"tag":"TypeConstructor","contents":[["Effect"],"Effect"]},{"annotation":[],"tag":"TypeConstructor","contents":[["Web","DOM","Internal","Types"],"NodeList"]}]}]}]}},"sourceSpan":{"start":[56,1],"name":".spago/web-dom/v4.0.0/src/Web/DOM/ParentNode.purs","end":[56,82]}}]}